simpler/__init__.py
simpler/_version.py
simpler/algorithms.py
simpler/bioinformatics.py
simpler/connectors.py
simpler/files.py
simpler/format.py
simpler/mail.py
simpler/math.py
simpler/profiling.py
simpler/sparql.py
simpler/terminal.py
simpler/tests.py
simpler/validation.py
simpler/web.py
simpler-7.0.2.dist-info/LICENSE
simpler-7.0.2.dist-info/METADATA
simpler-7.0.2.dist-info/WHEEL
simpler-7.0.2.dist-info/top_level.txt
simpler-7.0.2.dist-info/RECORD
