Metadata-Version: 2.1
Name: simpler
Version: 7.0.2
Summary: Makes Python simpler.
Home-page: https://github.com/juancroldan/simpler
Author: Juan C. Roldán
Author-email: juancarlos@sevilla.es
License: MIT
Classifier: Development Status :: 5 - Production/Stable
Classifier: Intended Audience :: Developers
Classifier: License :: OSI Approved :: MIT License
Classifier: Programming Language :: Python :: 3
License-File: LICENSE
Requires-Dist: requests>=2.13.0
Requires-Dist: pandas
Requires-Dist: pyyaml
Requires-Dist: rarfile
Requires-Dist: py7zr
Requires-Dist: sphinx_autodoc_typehints
Requires-Dist: elevate>=0.1.3
